{"_total":22,"_totalPage":3,"_page":3,"posts":[{"tags":[{"name":"hexo","permalink":"/tags/hexo/","url":"\\async\\tags\\hexo.json","count":1}],"categories":[],"url":"\\async\\posts\\2014\\05\\24\\build-blog-with-hexo.json","date":1400896146000,"path":{"year":2014,"month":5,"day":24,"name":"build-blog-with-hexo"},"title":"Hexo搭建个人博客","permalink":"/2014/05/24/build-blog-with-hexo/","content":"<p>　　一直想搭建一个自己的博客来记录自己的一些学习笔记，由于是学生党经济上有些吃紧所以一直没办法搭建起自己的博客。最近在网上无意中看到了可以借助GitHub来搭建自己的个人博客，于是就折腾了起来。我搭建博客用到的是GitHub+Hexo的搭配，下面就让我来介绍下我的博客搭建的整个过程。<br>"},{"tags":[{"name":"markdown","permalink":"/tags/markdown/","url":"\\async\\tags\\markdown.json","count":1}],"categories":[],"url":"\\async\\posts\\2014\\05\\24\\overview-of-markdown.json","date":1400896083000,"path":{"year":2014,"month":5,"day":24,"name":"overview-of-markdown"},"title":"Markdown初探","permalink":"/2014/05/24/overview-of-markdown/","content":"<p>听说Markdown是在很早以前了，可是一直不知道这是用来干嘛的。这次由于使用Hexo搭建了博客需要使用Markdown来写博客，专门了解了一下。</p>"}]}